context_window_manager/__init__.py
context_window_manager/manager.py
context_window_manager/types.py
context_window_manager-0.1.0.dist-info/licenses/LICENSE
context_window_manager-0.1.0.dist-info/METADATA
context_window_manager-0.1.0.dist-info/WHEEL
context_window_manager-0.1.0.dist-info/top_level.txt
context_window_manager-0.1.0.dist-info/RECORD
