Metadata-Version: 2.4
Name: context-window-manager
Version: 0.1.0
Summary: Production-ready LLM context window optimization and management
Author-email: Pranay M <pranay@example.com>
License: MIT
Project-URL: Homepage, https://github.com/pranaym/context-window-manager
Project-URL: Documentation, https://github.com/pranaym/context-window-manager#readme
Project-URL: Repository, https://github.com/pranaym/context-window-manager
Keywords: llm,context,tokens,gpt,claude,optimization
Classifier: Development Status :: 4 - Beta
Classifier: Intended Audience :: Developers
Classifier: License :: OSI Approved :: MIT License
Classifier: Programming Language :: Python :: 3
Classifier: Programming Language :: Python :: 3.8
Classifier: Programming Language :: Python :: 3.9
Classifier: Programming Language :: Python :: 3.10
Classifier: Programming Language :: Python :: 3.11
Classifier: Programming Language :: Python :: 3.12
Classifier: Topic :: Scientific/Engineering :: Artificial Intelligence
Requires-Python: >=3.8
License-File: LICENSE
Provides-Extra: tiktoken
Requires-Dist: tiktoken>=0.5.0; extra == "tiktoken"
Provides-Extra: full
Requires-Dist: tiktoken>=0.5.0; extra == "full"
Provides-Extra: dev
Requires-Dist: pytest>=7.0.0; extra == "dev"
Requires-Dist: black>=23.0.0; extra == "dev"
Requires-Dist: mypy>=1.0.0; extra == "dev"
Dynamic: license-file
